kflearn/__init__.py
kflearn/config_ini.py
kflearn/config_ops.py
kflearn/constant_utils.py
kflearn/data_ops.py
kflearn/file_util.py
kflearn/logging.py
kflearn/metrics_ops.py
kflearn/model_ops.py
kflearn/setup.py
kflearn/train_ops.py
kflearn-1.0.0.dist-info/DESCRIPTION.rst
kflearn-1.0.0.dist-info/METADATA
kflearn-1.0.0.dist-info/RECORD
kflearn-1.0.0.dist-info/WHEEL
kflearn-1.0.0.dist-info/metadata.json
kflearn-1.0.0.dist-info/top_level.txt
