Metadata-Version: 2.0
Name: kflearn
Version: 1.0.0
Summary: machine learning kit for algorithm train platform
Home-page: https://code.amh-group.com/model-platform/kflearn
Author: horn
Author-email: hongen26@163.com
License: MIT Licence
Project-URL: Documentation, https://packaging.python.org/tutorials/distributing-packages/
Project-URL: Funding, https://donate.pypi.org
Project-URL: Source, https://github.com/pypa/sampleproject/
Project-URL: Tracker, https://github.com/pypa/sampleproject/issues
Keywords: ga nn
Platform: UNKNOWN
Requires-Python: >=3
License-File: LICENSE
